doc_it/__init__.py
doc_it/main.py
doc_it/commands/__init__.py
doc_it/commands/commit.py
doc_it/commands/generate.py
doc_it/commands/init.py
doc_it/db/__init__.py
doc_it/db/database.py
doc_it/utils/__init__.py
doc_it/utils/config_handler.py
doc_it/utils/diff_util.py
doc_it/utils/doc_generator.py
doc_it/utils/llm_util.py
doc_it_installer-0.1.3.dist-info/METADATA
doc_it_installer-0.1.3.dist-info/WHEEL
doc_it_installer-0.1.3.dist-info/entry_points.txt
doc_it_installer-0.1.3.dist-info/top_level.txt
doc_it_installer-0.1.3.dist-info/RECORD
