Metadata-Version: 2.4
Name: doc-it-installer
Version: 0.1.3
Summary: A modular CLI tool to automatically generate documentation for code changes using a local Ollama LLM.
Author-email: "Kartik Sharma, Harshvardhan Singh" <kartiksh1610@gmail.com>
Classifier: Programming Language :: Python :: 3
Classifier: License :: OSI Approved :: MIT License
Classifier: Operating System :: OS Independent
Classifier: Topic :: Software Development :: Documentation
Requires-Python: >=3.10
Requires-Dist: typer[all]
Requires-Dist: rich
Requires-Dist: requests
Requires-Dist: python-docx
Requires-Dist: PyLaTeX
